Workbook

Sheet Sample - Superstore-1
A1: Row ID | B1: Order ID | C1: Order Date | D1: Ship Date | E1: Ship Mode | F1: Customer ID | G1: Customer Name | H1: Segment | I1: Country | J1: City | K1: State | L1: Postal Code | M1: Region | N1: Product ID | O1: Category | P1: Sub-Category | Q1: Product Name | R1: Sales | S1: Quantity | T1: Discount | U1: Profit
A2: 1 | B2: CA-2016-152156 | C2: 42682 | D2: 42685 | E2: Second Class | F2: CG-12520 | G2: Claire Gute | H2: Consumer | I2: United States | J2: Henderson | K2: Kentucky | L2: 42420 | M2: South | N2: FUR-BO-10001798 | O2: Furniture | P2: Bookcases | Q2: Bush Somerset Collection Bookcase | R2: 261.96 | S2: 2 | T2: 0 | U2: 41.9136
A3: 2 | B3: CA-2016-152156 | C3: 42682 | D3: 42685 | E3: Second Class | F3: CG-12520 | G3: Claire Gute | H3: Consumer | I3: United States | J3: Henderson | K3: Kentucky | L3: 42420 | M3: South | N3: FUR-CH-10000454 | O3: Furniture | P3: Chairs | Q3: Hon Deluxe Fabric Upholstered Stacking Chairs, Rounded Back | R3: 731.94 | S3: 3 | T3: 0 | U3: 219.582
A4: 3 | B4: CA-2016-138688 | C4: 42533 | D4: 6/16/2016 | E4: Second Class | F4: DV-13045 | G4: Darrin Van Huff | H4: Corporate | I4: United States | J4: Los Angeles | K4: California | L4: 90036 | M4: West | N4: OFF-LA-10000240 | O4: Office Supplies | P4: Labels | Q4: Self-Adhesive Address Labels for Typewriters by Universal | R4: 14.62 | S4: 2 | T4: 0 | U4: 6.8714
A5: 4 | B5: US-2015-108966 | C5: 42288 | D5: 10/18/2015 | E5: Standard Class | F5: SO-20335 | G5: Sean O'Donnell | H5: Consumer | I5: United States | J5: Fort Lauderdale | K5: Florida | L5: 33311 | M5: South | N5: FUR-TA-10000577 | O5: Furniture | P5: Tables | Q5: Bretford CR4500 Series Slim Rectangular Table | R5: 957.5775 | S5: 5 | T5: 0.45 | U5: -383.031
A6: 5 | B6: US-2015-108966 | C6: 42288 | D6: 10/18/2015 | E6: Standard Class | F6: SO-20335 | G6: Sean O'Donnell | H6: Consumer | I6: United States | J6: Fort Lauderdale | K6: Florida | L6: 33311 | M6: South | N6: OFF-ST-10000760 | O6: Office Supplies | P6: Storage | Q6: Eldon Fold 'N Roll Cart System | R6: 22.368 | S6: 2 | T6: 0.2 | U6: 2.5164
A7: 6 | B7: CA-2014-115812 | C7: 41799 | D7: 6/14/2014 | E7: Standard Class | F7: BH-11710 | G7: Brosina Hoffman | H7: Consumer | I7: United States | J7: Los Angeles | K7: California | L7: 90032 | M7: West | N7: FUR-FU-10001487 | O7: Furniture | P7: Furnishings | Q7: Eldon Expressions Wood and Plastic Desk Accessories, Cherry Wood | R7: 48.86 | S7: 7 | T7: 0 | U7: 14.1694
A8: 7 | B8: CA-2014-115812 | C8: 41799 | D8: 6/14/2014 | E8: Standard Class | F8: BH-11710 | G8: Brosina Hoffman | H8: Consumer | I8: United States | J8: Los Angeles | K8: California | L8: 90032 | M8: West | N8: OFF-AR-10002833 | O8: Office Supplies | P8: Art | Q8: Newell 322 | R8: 7.28 | S8: 4 | T8: 0 | U8: 1.9656
A9: 8 | B9: CA-2014-115812 | C9: 41799 | D9: 6/14/2014 | E9: Standard Class | F9: BH-11710 | G9: Brosina Hoffman | H9: Consumer | I9: United States | J9: Los Angeles | K9: California | L9: 90032 | M9: West | N9: TEC-PH-10002275 | O9: Technology | P9: Phones | Q9: Mitel 5320 IP Phone VoIP phone | R9: 907.152 | S9: 6 | T9: 0.2 | U9: 90.7152
A10: 9 | B10: CA-2014-115812 | C10: 41799 | D10: 6/14/2014 | E10: Standard Class | F10: BH-11710 | G10: Brosina Hoffman | H10: Consumer | I10: United States | J10: Los Angeles | K10: California | L10: 90032 | M10: West | N10: OFF-BI-10003910 | O10: Office Supplies | P10: Binders | Q10: DXL Angle-View Binders with Locking Rings by Samsill | R10: 18.504 | S10: 3 | T10: 0.2 | U10: 5.7825
A11: 10 | B11: CA-2014-115812 | C11: 41799 | D11: 6/14/2014 | E11: Standard Class | F11: BH-11710 | G11: Brosina Hoffman | H11: Consumer | I11: United States | J11: Los Angeles | K11: California | L11: 90032 | M11: West | N11: OFF-AP-10002892 | O11: Office Supplies | P11: Appliances | Q11: Belkin F5C206VTEL 6 Outlet Surge | R11: 114.9 | S11: 5 | T11: 0 | U11: 34.47
A12: 11 | B12: CA-2014-115812 | C12: 41799 | D12: 6/14/2014 | E12: Standard Class | F12: BH-11710 | G12: Brosina Hoffman | H12: Consumer | I12: United States | J12: Los Angeles | K12: California | L12: 90032 | M12: West | N12: FUR-TA-10001539 | O12: Furniture | P12: Tables | Q12: Chromcraft Rectangular Conference Tables | R12: 1706.184 | S12: 9 | T12: 0.2 | U12: 85.3092
A13: 12 | B13: CA-2014-115812 | C13: 41799 | D13: 6/14/2014 | E13: Standard Class | F13: BH-11710 | G13: Brosina Hoffman | H13: Consumer | I13: United States | J13: Los Angeles | K13: California | L13: 90032 | M13: West | N13: TEC-PH-10002033 | O13: Technology | P13: Phones | Q13: Konftel 250 Conference†phone†- Charcoal black | R13: 911.424 | S13: 4 | T13: 0.2 | U13: 68.3568
A14: 13 | B14: CA-2017-114412 | C14: 42840 | D14: 4/20/2017 | E14: Standard Class | F14: AA-10480 | G14: Andrew Allen | H14: Consumer | I14: United States | J14: Concord | K14: North Carolina | L14: 28027 | M14: South | N14: OFF-PA-10002365 | O14: Office Supplies | P14: Paper | Q14: Xerox 1967 | R14: 15.552 | S14: 3 | T14: 0.2 | U14: 5.4432
A15: 14 | B15: CA-2016-161389 | C15: 42709 | D15: 42655 | E15: Standard Class | F15: IM-15070 | G15: Irene Maddox | H15: Consumer | I15: United States | J15: Seattle | K15: Washington | L15: 98103 | M15: West | N15: OFF-BI-10003656 | O15: Office Supplies | P15: Binders | Q15: Fellowes PB200 Plastic Comb Binding Machine | R15: 407.976 | S15: 3 | T15: 0.2 | U15: 132.5922
A16: 15 | B16: US-2015-118983 | C16: 42330 | D16: 11/26/2015 | E16: Standard Class | F16: HP-14815 | G16: Harold Pawlan | H16: Home Office | I16: United States | J16: Fort Worth | K16: Texas | L16: 76106 | M16: Central | N16: OFF-AP-10002311 | O16: Office Supplies | P16: Appliances | Q16: Holmes Replacement Filter for HEPA Air Cleaner, Very Large Room, HEPA Filter | R16: 68.81 | S16: 5 | T16: 0.8 | U16: -123.858
A17: 16 | B17: US-2015-118983 | C17: 42330 | D17: 11/26/2015 | E17: Standard Class | F17: HP-14815 | G17: Harold Pawlan | H17: Home Office | I17: United States | J17: Fort Worth | K17: Texas | L17: 76106 | M17: Central | N17: OFF-BI-10000756 | O17: Office Supplies | P17: Binders | Q17: Storex DuraTech Recycled Plastic Frosted Binders | R17: 2.544 | S17: 3 | T17: 0.8 | U17: -3.816
A18: 17 | B18: CA-2014-105893 | C18: 41954 | D18: 11/18/2014 | E18: Standard Class | F18: PK-19075 | G18: Pete Kriz | H18: Consumer | I18: United States | J18: Madison | K18: Wisconsin | L18: 53711 | M18: Central | N18: OFF-ST-10004186 | O18: Office Supplies | P18: Storage | Q18: Stur-D-Stor Shelving, Vertical 5-Shelf: 72"H x 36"W x 18 1/2"D | R18: 665.88 | S18: 6 | T18: 0 | U18: 13.3176
A19: 18 | B19: CA-2014-167164 | C19: 41772 | D19: 5/15/2014 | E19: Second Class | F19: AG-10270 | G19: Alejandro Grove | H19: Consumer | I19: United States | J19: West Jordan | K19: Utah | L19: 84084 | M19: West | N19: OFF-ST-10000107 | O19: Office Supplies | P19: Storage | Q19: Fellowes Super Stor/Drawer | R19: 55.5 | S19: 2 | T19: 0 | U19: 9.99
A20: 19 | B20: CA-2014-143336 | C20: 41878 | D20: 41648 | E20: Second Class | F20: ZD-21925 | G20: Zuschuss Donatelli | H20: Consumer | I20: United States | J20: San Francisco | K20: California | L20: 94109 | M20: West | N20: OFF-AR-10003056 | O20: Office Supplies | P20: Art | Q20: Newell 341 | R20: 8.56 | S20: 2 | T20: 0 | U20: 2.4824
A21: 20 | B21: CA-2014-143336 | C21: 41878 | D21: 41648 | E21: Second Class | F21: ZD-21925 | G21: Zuschuss Donatelli | H21: Consumer | I21: United States | J21: San Francisco | K21: California | L21: 94109 | M21: West | N21: TEC-PH-10001949 | O21: Technology | P21: Phones | Q21: Cisco SPA 501G IP Phone | R21: 213.48 | S21: 3 | T21: 0.2 | U21: 16.011
A22: 21 | B22: CA-2014-143336 | C22: 41878 | D22: 41648 | E22: Second Class | F22: ZD-21925 | G22: Zuschuss Donatelli | H22: Consumer | I22: United States | J22: San Francisco | K22: California | L22: 94109 | M22: West | N22: OFF-BI-10002215 | O22: Office Supplies | P22: Binders | Q22: Wilson Jones Hanging View Binder, White, 1" | R22: 22.72 | S22: 4 | T22: 0.2 | U22: 7.384
A23: 22 | B23: CA-2016-137330 | C23: 42713 | D23: 12/13/2016 | E23: Standard Class | F23: KB-16585 | G23: Ken Black | H23: Corporate | I23: United States | J23: Fremont | K23: Nebraska | L23: 68025 | M23: Central | N23: OFF-AR-10000246 | O23: Office Supplies | P23: Art | Q23: Newell 318 | R23: 19.46 | S23: 7 | T23: 0 | U23: 5.0596
A24: 23 | B24: CA-2016-137330 | C24: 42713 | D24: 12/13/2016 | E24: Standard Class | F24: KB-16585 | G24: Ken Black | H24: Corporate | I24: United States | J24: Fremont | K24: Nebraska | L24: 68025 | M24: Central | N24: OFF-AP-10001492 | O24: Office Supplies | P24: Appliances | Q24: Acco Six-Outlet Power Strip, 4' Cord Length | R24: 60.34 | S24: 7 | T24: 0 | U24: 15.6884
A25: 24 | B25: US-2017-156909 | C25: 42932 | D25: 7/18/2017 | E25: Second Class | F25: SF-20065 | G25: Sandra Flanagan | H25: Consumer | I25: United States | J25: Philadelphia | K25: Pennsylvania | L25: 19140 | M25: East | N25: FUR-CH-10002774 | O25: Furniture | P25: Chairs | Q25: Global Deluxe Stacking Chair, Gray | R25: 71.372 | S25: 2 | T25: 0.3 | U25: -1.0196
A26: 25 | B26: CA-2015-106320 | C26: 42272 | D26: 9/30/2015 | E26: Standard Class | F26: EB-13870 | G26: Emily Burns | H26: Consumer | I26: United States | J26: Orem | K26: Utah | L26: 84057 | M26: West | N26: FUR-TA-10000577 | O26: Furniture | P26: Tables | Q26: Bretford CR4500 Series Slim Rectangular Table | R26: 1044.63 | S26: 3 | T26: 0 | U26: 240.2649
A27: 26 | B27: CA-2016-121755 | C27: 42385 | D27: 1/20/2016 | E27: Second Class | F27: EH-13945 | G27: Eric Hoffmann | H27: Consumer | I27: United States | J27: Los Angeles | K27: California | L27: 90049 | M27: West | N27: OFF-BI-10001634 | O27: Office Supplies | P27: Binders | Q27: Wilson Jones Active Use Binders | R27: 11.648 | S27: 2 | T27: 0.2 | U27: 4.2224
A28: 27 | B28: CA-2016-121755 | C28: 42385 | D28: 1/20/2016 | E28: Second Class | F28: EH-13945 | G28: Eric Hoffmann | H28: Consumer | I28: United States | J28: Los Angeles | K28: California | L28: 90049 | M28: West | N28: TEC-AC-10003027 | O28: Technology | P28: Accessories | Q28: Imation†8GB Mini TravelDrive USB 2.0†Flash Drive | R28: 90.57 | S28: 3 | T28: 0 | U28: 11.7741
A29: 28 | B29: US-2015-150630 | C29: 42264 | D29: 9/21/2015 | E29: Standard Class | F29: TB-21520 | G29: Tracy Blumstein | H29: Consumer | I29: United States | J29: Philadelphia | K29: Pennsylvania | L29: 19140 | M29: East | N29: FUR-BO-10004834 | O29: Furniture | P29: Bookcases | Q29: Riverside Palais Royal Lawyers Bookcase, Royale Cherry Finish | R29: 3083.43 | S29: 7 | T29: 0.5 | U29: -1665.0522
A30: 29 | B30: US-2015-150630 | C30: 42264 | D30: 9/21/2015 | E30: Standard Class | F30: TB-21520 | G30: Tracy Blumstein | H30: Consumer | I30: United States | J30: Philadelphia | K30: Pennsylvania | L30: 19140 | M30: East | N30: OFF-BI-10000474 | O30: Office Supplies | P30: Binders | Q30: Avery Recycled Flexi-View Covers for Binding Systems | R30: 9.618 | S30: 2 | T30: 0.7 | U30: -7.0532
A31: 30 | B31: US-2015-150630 | C31: 42264 | D31: 9/21/2015 | E31: Standard Class | F31: TB-21520 | G31: Tracy Blumstein | H31: Consumer | I31: United States | J31: Philadelphia | K31: Pennsylvania | L31: 19140 | M31: East | N31: FUR-FU-10004848 | O31: Furniture | P31: Furnishings | Q31: Howard Miller 13-3/4" Diameter Brushed Chrome Round Wall Clock | R31: 124.2 | S31: 3 | T31: 0.2 | U31: 15.525
A32: 31 | B32: US-2015-150630 | C32: 42264 | D32: 9/21/2015 | E32: Standard Class | F32: TB-21520 | G32: Tracy Blumstein | H32: Consumer | I32: United States | J32: Philadelphia | K32: Pennsylvania | L32: 19140 | M32: East | N32: OFF-EN-10001509 | O32: Office Supplies | P32: Envelopes | Q32: Poly String Tie Envelopes | R32: 3.264 | S32: 2 | T32: 0.2 | U32: 1.1016
A33: 32 | B33: US-2015-150630 | C33: 42264 | D33: 9/21/2015 | E33: Standard Class | F33: TB-21520 | G33: Tracy Blumstein | H33: Consumer | I33: United States | J33: Philadelphia | K33: Pennsylvania | L33: 19140 | M33: East | N33: OFF-AR-10004042 | O33: Office Supplies | P33: Art | Q33: BOSTON Model 1800 Electric Pencil Sharpeners, Putty/Woodgrain | R33: 86.304 | S33: 6 | T33: 0.2 | U33: 9.7092
A34: 33 | B34: US-2015-150630 | C34: 42264 | D34: 9/21/2015 | E34: Standard Class | F34: TB-21520 | G34: Tracy Blumstein | H34: Consumer | I34: United States | J34: Philadelphia | K34: Pennsylvania | L34: 19140 | M34: East | N34: OFF-BI-10001525 | O34: Office Supplies | P34: Binders | Q34: Acco Pressboard Covers with Storage Hooks, 14 7/8" x 11", Executive Red | R34: 6.858 | S34: 6 | T34: 0.7 | U34: -5.715
... A36: 35 | B36: CA-2017-107727 | C36: 43027 | D36: 10/23/2017 | E36: Second Class | F36: MA-17560 | G36: Matt Abelman | H36: Home Office | I36: United States | J36: Houston | K36: Texas | L36: 77095 | M36: Central | N36: OFF-PA-10000249 | O36: Office Supplies | P36: Paper | Q36: Easy-staple paper | R36: 29.472 | S36: 3 | T36: 0.2 | U36: 9.9468
A37: 36 | B37: CA-2016-117590 | C37: 42712 | D37: 42655 | E37: First Class | F37: GH-14485 | G37: Gene Hale | H37: Corporate | I37: United States | J37: Richardson | K37: Texas | L37: 75080 | M37: Central | N37: TEC-PH-10004977 | O37: Technology | P37: Phones | Q37: GE 30524EE4 | R37: 1097.544 | S37: 7 | T37: 0.2 | U37: 123.4737
A38: 37 | B38: CA-2016-117590 | C38: 42712 | D38: 42655 | E38: First Class | F38: GH-14485 | G38: Gene Hale | H38: Corporate | I38: United States | J38: Richardson | K38: Texas | L38: 75080 | M38: Central | N38: FUR-FU-10003664 | O38: Furniture | P38: Furnishings | Q38: Electrix Architect's Clamp-On Swing Arm Lamp, Black | R38: 190.92 | S38: 5 | T38: 0.6 | U38: -147.963
A39: 38 | B39: CA-2015-117415 | C39: 42365 | D39: 12/31/2015 | E39: Standard Class | F39: SN-20710 | G39: Steve Nguyen | H39: Home Office | I39: United States | J39: Houston | K39: Texas | L39: 77041 | M39: Central | N39: OFF-EN-10002986 | O39: Office Supplies | P39: Envelopes | Q39: #10-4 1/8" x 9 1/2" Premium Diagonal Seam Envelopes | R39: 113.328 | S39: 9 | T39: 0.2 | U39: 35.415
A40: 39 | B40: CA-2015-117415 | C40: 42365 | D40: 12/31/2015 | E40: Standard Class | F40: SN-20710 | G40: Steve Nguyen | H40: Home Office | I40: United States | J40: Houston | K40: Texas | L40: 77041 | M40: Central | N40: FUR-BO-10002545 | O40: Furniture | P40: Bookcases | Q40: Atlantic Metals Mobile 3-Shelf Bookcases, Custom Colors | R40: 532.3992 | S40: 3 | T40: 0.32 | U40: -46.9764
A41: 40 | B41: CA-2015-117415 | C41: 42365 | D41: 12/31/2015 | E41: Standard Class | F41: SN-20710 | G41: Steve Nguyen | H41: Home Office | I41: United States | J41: Houston | K41: Texas | L41: 77041 | M41: Central | N41: FUR-CH-10004218 | O41: Furniture | P41: Chairs | Q41: Global Fabric Manager's Chair, Dark Gray | R41: 212.058 | S41: 3 | T41: 0.3 | U41: -15.147
A42: 41 | B42: CA-2015-117415 | C42: 42365 | D42: 12/31/2015 | E42: Standard Class | F42: SN-20710 | G42: Steve Nguyen | H42: Home Office | I42: United States | J42: Houston | K42: Texas | L42: 77041 | M42: Central | N42: TEC-PH-10000486 | O42: Technology | P42: Phones | Q42: Plantronics HL10 Handset Lifter | R42: 371.168 | S42: 4 | T42: 0.2 | U42: 41.7564
A43: 42 | B43: CA-2017-120999 | C43: 42988 | D43: 9/15/2017 | E43: Standard Class | F43: LC-16930 | G43: Linda Cazamias | H43: Corporate | I43: United States | J43: Naperville | K43: Illinois | L43: 60540 | M43: Central | N43: TEC-PH-10004093 | O43: Technology | P43: Phones | Q43: Panasonic Kx-TS550 | R43: 147.168 | S43: 4 | T43: 0.2 | U43: 16.5564
A44: 43 | B44: CA-2016-101343 | C44: 42568 | D44: 7/22/2016 | E44: Standard Class | F44: RA-19885 | G44: Ruben Ausman | H44: Corporate | I44: United States | J44: Los Angeles | K44: California | L44: 90049 | M44: West | N44: OFF-ST-10003479 | O44: Office Supplies | P44: Storage | Q44: Eldon Base for stackable storage shelf, platinum | R44: 77.88 | S44: 2 | T44: 0 | U44: 3.894
A45: 44 | B45: CA-2017-139619 | C45: 42997 | D45: 9/23/2017 | E45: Standard Class | F45: ES-14080 | G45: Erin Smith | H45: Corporate | I45: United States | J45: Melbourne | K45: Florida | L45: 32935 | M45: South | N45: OFF-ST-10003282 | O45: Office Supplies | P45: Storage | Q45: Advantus 10-Drawer Portable Organizer, Chrome Metal Frame, Smoke Drawers | R45: 95.616 | S45: 2 | T45: 0.2 | U45: 9.5616
A46: 45 | B46: CA-2016-118255 | C46: 42440 | D46: 3/13/2016 | E46: First Class | F46: ON-18715 | G46: Odella Nelson | H46: Corporate | I46: United States | J46: Eagan | K46: Minnesota | L46: 55122 | M46: Central | N46: TEC-AC-10000171 | O46: Technology | P46: Accessories | Q46: Verbatim 25 GB 6x Blu-ray Single Layer Recordable Disc, 25/Pack | R46: 45.98 | S46: 2 | T46: 0 | U46: 19.7714
A47: 46 | B47: CA-2016-118255 | C47: 42440 | D47: 3/13/2016 | E47: First Class | F47: ON-18715 | G47: Odella Nelson | H47: Corporate | I47: United States | J47: Eagan | K47: Minnesota | L47: 55122 | M47: Central | N47: OFF-BI-10003291 | O47: Office Supplies | P47: Binders | Q47: Wilson Jones Leather-Like Binders with DublLock Round Rings | R47: 17.46 | S47: 2 | T47: 0 | U47: 8.2062
A48: 47 | B48: CA-2014-146703 | C48: 41932 | D48: 10/25/2014 | E48: Second Class | F48: PO-18865 | G48: Patrick O'Donnell | H48: Consumer | I48: United States | J48: Westland | K48: Michigan | L48: 48185 | M48: Central | N48: OFF-ST-10001713 | O48: Office Supplies | P48: Storage | Q48: Gould Plastics 9-Pocket Panel Bin, 18-3/8w x 5-1/4d x 20-1/2h, Black | R48: 211.96 | S48: 4 | T48: 0 | U48: 8.4784
A49: 48 | B49: CA-2016-169194 | C49: 42541 | D49: 6/25/2016 | E49: Standard Class | F49: LH-16900 | G49: Lena Hernandez | H49: Consumer | I49: United States | J49: Dover | K49: Delaware | L49: 19901 | M49: East | N49: TEC-AC-10002167 | O49: Technology | P49: Accessories | Q49: Imation†8gb Micro Traveldrive Usb 2.0†Flash Drive | R49: 45 | S49: 3 | T49: 0 | U49: 4.95
A50: 49 | B50: CA-2016-169194 | C50: 42541 | D50: 6/25/2016 | E50: Standard Class | F50: LH-16900 | G50: Lena Hernandez | H50: Consumer | I50: United States | J50: Dover | K50: Delaware | L50: 19901 | M50: East | N50: TEC-PH-10003988 | O50: Technology | P50: Phones | Q50: LF Elite 3D Dazzle Designer Hard Case Cover, Lf Stylus Pen and Wiper For Apple Iphone 5c Mini Lite | R50: 21.8 | S50: 2 | T50: 0 | U50: 6.104
... A67: 66 | B67: CA-2015-135545 | C67: 42332 | D67: 11/30/2015 | E67: Standard Class | F67: KM-16720 | G67: Kunst Miller | H67: Consumer | I67: United States | J67: Los Angeles | K67: California | L67: 90004 | M67: West | N67: FUR-FU-10000397 | O67: Furniture | P67: Furnishings | Q67: Luxo Economy Swing Arm Lamp | R67: 79.76 | S67: 4 | T67: 0 | U67: 22.3328
A68: 67 | B68: US-2015-164175 | C68: 42124 | D68: 42129 | E68: Standard Class | F68: PS-18970 | G68: Paul Stevenson | H68: Home Office | I68: United States | J68: Chicago | K68: Illinois | L68: 60610 | M68: Central | N68: FUR-CH-10001146 | O68: Furniture | P68: Chairs | Q68: Global Value Mid-Back Manager's Chair, Gray | R68: 213.115 | S68: 5 | T68: 0.3 | U68: -15.2225
A69: 68 | B69: CA-2014-106376 | C69: 41978 | D69: 41924 | E69: Standard Class | F69: BS-11590 | G69: Brendan Sweed | H69: Corporate | I69: United States | J69: Gilbert | K69: Arizona | L69: 85234 | M69: West | N69: OFF-AR-10002671 | O69: Office Supplies | P69: Art | Q69: Hunt BOSTON Model 1606 High-Volume Electric Pencil Sharpener, Beige | R69: 1113.024 | S69: 8 | T69: 0.2 | U69: 111.3024
A70: 69 | B70: CA-2014-106376 | C70: 41978 | D70: 41924 | E70: Standard Class | F70: BS-11590 | G70: Brendan Sweed | H70: Corporate | I70: United States | J70: Gilbert | K70: Arizona | L70: 85234 | M70: West | N70: TEC-PH-10002726 | O70: Technology | P70: Phones | Q70: netTALK DUO VoIP Telephone Service | R70: 167.968 | S70: 4 | T70: 0.2 | U70: 62.988
A71: 70 | B71: CA-2016-119823 | C71: 42525 | D71: 42527 | E71: First Class | F71: KD-16270 | G71: Karen Daniels | H71: Consumer | I71: United States | J71: Springfield | K71: Virginia | L71: 22153 | M71: South | N71: OFF-PA-10000482 | O71: Office Supplies | P71: Paper | Q71: Snap-A-Way Black Print Carbonless Ruled Speed Letter, Triplicate | R71: 75.88 | S71: 2 | T71: 0 | U71: 35.6636
A72: 71 | B72: CA-2016-106075 | C72: 42631 | D72: 9/23/2016 | E72: Standard Class | F72: HM-14980 | G72: Henry MacAllister | H72: Consumer | I72: United States | J72: New York City | K72: New York | L72: 10009 | M72: East | N72: OFF-BI-10004654 | O72: Office Supplies | P72: Binders | Q72: Avery Binding System Hidden Tab Executive Style Index Sets | R72: 4.616 | S72: 1 | T72: 0.2 | U72: 1.731
A73: 72 | B73: CA-2017-114440 | C73: 42992 | D73: 9/17/2017 | E73: Second Class | F73: TB-21520 | G73: Tracy Blumstein | H73: Consumer | I73: United States | J73: Jackson | K73: Michigan | L73: 49201 | M73: Central | N73: OFF-PA-10004675 | O73: Office Supplies | P73: Paper | Q73: Telephone Message Books with Fax/Mobile Section, 5 1/2" x 3 3/16" | R73: 19.05 | S73: 3 | T73: 0 | U73: 8.763
A74: 73 | B74: US-2015-134026 | C74: 42120 | D74: 42040 | E74: Standard Class | F74: JE-15745 | G74: Joel Eaton | H74: Consumer | I74: United States | J74: Memphis | K74: Tennessee | L74: 38109 | M74: South | N74: FUR-CH-10000513 | O74: Furniture | P74: Chairs | Q74: High-Back Leather Manager's Chair | R74: 831.936 | S74: 8 | T74: 0.2 | U74: -114.3912
A75: 74 | B75: US-2015-134026 | C75: 42120 | D75: 42040 | E75: Standard Class | F75: JE-15745 | G75: Joel Eaton | H75: Consumer | I75: United States | J75: Memphis | K75: Tennessee | L75: 38109 | M75: South | N75: FUR-FU-10003708 | O75: Furniture | P75: Furnishings | Q75: Tenex Traditional Chairmats for Medium Pile Carpet, Standard Lip, 36" x 48" | R75: 97.04 | S75: 2 | T75: 0.2 | U75: 1.213
A76: 75 | B76: US-2015-134026 | C76: 42120 | D76: 42040 | E76: Standard Class | F76: JE-15745 | G76: Joel Eaton | H76: Consumer | I76: United States | J76: Memphis | K76: Tennessee | L76: 38109 | M76: South | N76: OFF-ST-10004123 | O76: Office Supplies | P76: Storage | Q76: Safco Industrial Wire Shelving System | R76: 72.784 | S76: 1 | T76: 0.2 | U76: -18.196
A77: 76 | B77: US-2017-118038 | C77: 43078 | D77: 43051 | E77: First Class | F77: KB-16600 | G77: Ken Brennan | H77: Corporate | I77: United States | J77: Houston | K77: Texas | L77: 77041 | M77: Central | N77: OFF-BI-10004182 | O77: Office Supplies | P77: Binders | Q77: Economy Binders | R77: 1.248 | S77: 3 | T77: 0.8 | U77: -1.9344
A78: 77 | B78: US-2017-118038 | C78: 43078 | D78: 43051 | E78: First Class | F78: KB-16600 | G78: Ken Brennan | H78: Corporate | I78: United States | J78: Houston | K78: Texas | L78: 77041 | M78: Central | N78: FUR-FU-10000260 | O78: Furniture | P78: Furnishings | Q78: 6" Cubicle Wall Clock, Black | R78: 9.708 | S78: 3 | T78: 0.6 | U78: -5.8248
A79: 78 | B79: US-2017-118038 | C79: 43078 | D79: 43051 | E79: First Class | F79: KB-16600 | G79: Ken Brennan | H79: Corporate | I79: United States | J79: Houston | K79: Texas | L79: 77041 | M79: Central | N79: OFF-ST-10000615 | O79: Office Supplies | P79: Storage | Q79: SimpliFile Personal File, Black Granite, 15w x 6-15/16d x 11-1/4h | R79: 27.24 | S79: 3 | T79: 0.2 | U79: 2.724
A80: 79 | B80: US-2014-147606 | C80: 41969 | D80: 41651 | E80: Second Class | F80: JE-15745 | G80: Joel Eaton | H80: Consumer | I80: United States | J80: Houston | K80: Texas | L80: 77070 | M80: Central | N80: FUR-FU-10003194 | O80: Furniture | P80: Furnishings | Q80: Eldon Expressions Desk Accessory, Wood Pencil Holder, Oak | R80: 19.3 | S80: 5 | T80: 0.6 | U80: -14.475
A81: 80 | B81: CA-2016-127208 | C81: 42533 | D81: 6/15/2016 | E81: First Class | F81: SC-20770 | G81: Stewart Carmichael | H81: Corporate | I81: United States | J81: Decatur | K81: Alabama | L81: 35601 | M81: South | N81: OFF-AP-10002118 | O81: Office Supplies | P81: Appliances | Q81: 1.7 Cubic Foot Compact "Cube" Office Refrigerators | R81: 208.16 | S81: 1 | T81: 0 | U81: 56.2032
A82: 81 | B82: CA-2016-127208 | C82: 42533 | D82: 6/15/2016 | E82: First Class | F82: SC-20770 | G82: Stewart Carmichael | H82: Corporate | I82: United States | J82: Decatur | K82: Alabama | L82: 35601 | M82: South | N82: OFF-BI-10002309 | O82: Office Supplies | P82: Binders | Q82: Avery Heavy-Duty EZD Binder With Locking Rings | R82: 16.74 | S82: 3 | T82: 0 | U82: 8.0352
A83: 82 | B83: CA-2014-139451 | C83: 41924 | D83: 10/16/2014 | E83: Standard Class | F83: DN-13690 | G83: Duane Noonan | H83: Consumer | I83: United States | J83: San Francisco | K83: California | L83: 94122 | M83: West | N83: OFF-AR-10002053 | O83: Office Supplies | P83: Art | Q83: Premium Writing Pencils, Soft, #2 by Central Association for the Blind | R83: 14.9 | S83: 5 | T83: 0 | U83: 4.172
A84: 83 | B84: CA-2014-139451 | C84: 41924 | D84: 10/16/2014 | E84: Standard Class | F84: DN-13690 | G84: Duane Noonan | H84: Consumer | I84: United States | J84: San Francisco | K84: California | L84: 94122 | M84: West | N84: OFF-ST-10002370 | O84: Office Supplies | P84: Storage | Q84: Sortfiler Multipurpose Personal File Organizer, Black | R84: 21.39 | S84: 1 | T84: 0 | U84: 6.2031
A85: 84 | B85: CA-2015-149734 | C85: 42250 | D85: 42225 | E85: Standard Class | F85: JC-16105 | G85: Julie Creighton | H85: Corporate | I85: United States | J85: Durham | K85: North Carolina | L85: 27707 | M85: South | N85: OFF-EN-10000927 | O85: Office Supplies | P85: Envelopes | Q85: Jet-Pak Recycled Peel 'N' Seal Padded Mailers | R85: 200.984 | S85: 7 | T85: 0.2 | U85: 62.8075
A86: 85 | B86: US-2017-119662 | C86: 43052 | D86: 11/16/2017 | E86: First Class | F86: CS-12400 | G86: Christopher Schild | H86: Home Office | I86: United States | J86: Chicago | K86: Illinois | L86: 60623 | M86: Central | N86: OFF-ST-10003656 | O86: Office Supplies | P86: Storage | Q86: Safco Industrial Wire Shelving | R86: 230.376 | S86: 3 | T86: 0.2 | U86: -48.9549
A87: 86 | B87: CA-2017-140088 | C87: 42883 | D87: 5/30/2017 | E87: Second Class | F87: PO-18865 | G87: Patrick O'Donnell | H87: Consumer | I87: United States | J87: Columbia | K87: South Carolina | L87: 29203 | M87: South | N87: FUR-CH-10000863 | O87: Furniture | P87: Chairs | Q87: Novimex Swivel Fabric Task Chair | R87: 301.96 | S87: 2 | T87: 0 | U87: 33.2156
A88: 87 | B88: CA-2017-155558 | C88: 43034 | D88: 42777 | E88: Standard Class | F88: PG-18895 | G88: Paul Gonzalez | H88: Consumer | I88: United States | J88: Rochester | K88: Minnesota | L88: 55901 | M88: Central | N88: TEC-AC-10001998 | O88: Technology | P88: Accessories | Q88: Logitech†LS21 Speaker System - PC Multimedia - 2.1-CH - Wired | R88: 19.99 | S88: 1 | T88: 0 | U88: 6.7966
A89: 88 | B89: CA-2017-155558 | C89: 43034 | D89: 42777 | E89: Standard Class | F89: PG-18895 | G89: Paul Gonzalez | H89: Consumer | I89: United States | J89: Rochester | K89: Minnesota | L89: 55901 | M89: Central | N89: OFF-LA-10000134 | O89: Office Supplies | P89: Labels | Q89: Avery 511 | R89: 6.16 | S89: 2 | T89: 0 | U89: 2.9568
A90: 89 | B90: CA-2016-159695 | C90: 42465 | D90: 42647 | E90: Second Class | F90: GM-14455 | G90: Gary Mitchum | H90: Home Office | I90: United States | J90: Houston | K90: Texas | L90: 77095 | M90: Central | N90: OFF-ST-10003442 | O90: Office Supplies | P90: Storage | Q90: Eldon Portable Mobile Manager | R90: 158.368 | S90: 7 | T90: 0.2 | U90: 13.8572
A91: 90 | B91: CA-2016-109806 | C91: 42630 | D91: 9/22/2016 | E91: Standard Class | F91: JS-15685 | G91: Jim Sink | H91: Corporate | I91: United States | J91: Los Angeles | K91: California | L91: 90036 | M91: West | N91: OFF-AR-10004930 | O91: Office Supplies | P91: Art | Q91: Turquoise Lead Holder with Pocket Clip | R91: 20.1 | S91: 3 | T91: 0 | U91: 6.633
A92: 91 | B92: CA-2016-109806 | C92: 42630 | D92: 9/22/2016 | E92: Standard Class | F92: JS-15685 | G92: Jim Sink | H92: Corporate | I92: United States | J92: Los Angeles | K92: California | L92: 90036 | M92: West | N92: TEC-PH-10004093 | O92: Technology | P92: Phones | Q92: Panasonic Kx-TS550 | R92: 73.584 | S92: 2 | T92: 0.2 | U92: 8.2782
A93: 92 | B93: CA-2016-109806 | C93: 42630 | D93: 9/22/2016 | E93: Standard Class | F93: JS-15685 | G93: Jim Sink | H93: Corporate | I93: United States | J93: Los Angeles | K93: California | L93: 90036 | M93: West | N93: OFF-PA-10000304 | O93: Office Supplies | P93: Paper | Q93: Xerox 1995 | R93: 6.48 | S93: 1 | T93: 0 | U93: 3.1104
A94: 93 | B94: CA-2015-149587 | C94: 42035 | D94: 42126 | E94: Second Class | F94: KB-16315 | G94: Karl Braun | H94: Consumer | I94: United States | J94: Minneapolis | K94: Minnesota | L94: 55407 | M94: Central | N94: OFF-PA-10003177 | O94: Office Supplies | P94: Paper | Q94: Xerox 1999 | R94: 12.96 | S94: 2 | T94: 0 | U94: 6.2208
A95: 94 | B95: CA-2015-149587 | C95: 42035 | D95: 42126 | E95: Second Class | F95: KB-16315 | G95: Karl Braun | H95: Consumer | I95: United States | J95: Minneapolis | K95: Minnesota | L95: 55407 | M95: Central | N95: FUR-FU-10003799 | O95: Furniture | P95: Furnishings | Q95: Seth Thomas 13 1/2" Wall Clock | R95: 53.34 | S95: 3 | T95: 0 | U95: 16.5354
A96: 95 | B96: CA-2015-149587 | C96: 42035 | D96: 42126 | E96: Second Class | F96: KB-16315 | G96: Karl Braun | H96: Consumer | I96: United States | J96: Minneapolis | K96: Minnesota | L96: 55407 | M96: Central | N96: OFF-BI-10002852 | O96: Office Supplies | P96: Binders | Q96: Ibico Standard Transparent Covers | R96: 32.96 | S96: 2 | T96: 0 | U96: 16.1504
A97: 96 | B97: US-2017-109484 | C97: 43045 | D97: 43080 | E97: Standard Class | F97: RB-19705 | G97: Roger Barcio | H97: Home Office | I97: United States | J97: Portland | K97: Oregon | L97: 97206 | M97: West | N97: OFF-BI-10004738 | O97: Office Supplies | P97: Binders | Q97: Flexible Leather- Look Classic Collection Ring Binder | R97: 5.682 | S97: 1 | T97: 0.7 | U97: -3.788
A98: 97 | B98: CA-2017-161018 | C98: 43048 | D98: 43050 | E98: Second Class | F98: PN-18775 | G98: Parhena Norris | H98: Home Office | I98: United States | J98: New York City | K98: New York | L98: 10009 | M98: East | N98: FUR-FU-10000629 | O98: Furniture | P98: Furnishings | Q98: 9-3/4 Diameter Round Wall Clock | R98: 96.53 | S98: 7 | T98: 0 | U98: 40.5426
A99: 98 | B99: CA-2017-157833 | C99: 42903 | D99: 6/20/2017 | E99: First Class | F99: KD-16345 | G99: Katherine Ducich | H99: Consumer | I99: United States | J99: San Francisco | K99: California | L99: 94122 | M99: West | N99: OFF-BI-10001721 | O99: Office Supplies | P99: Binders | Q99: Trimflex Flexible Post Binders | R99: 51.312 | S99: 3 | T99: 0.2 | U99: 17.9592
A100: 99 | B100: CA-2016-149223 | C100: 42619 | D100: 42683 | E100: Standard Class | F100: ER-13855 | G100: Elpida Rittenbach | H100: Corporate | I100: United States | J100: Saint Paul | K100: Minnesota | L100: 55106 | M100: Central | N100: OFF-AP-10000358 | O100: Office Supplies | P100: Appliances | Q100: Fellowes Basic Home/Office Series Surge Protectors | R100: 77.88 | S100: 6 | T100: 0 | U100: 22.5852
A101: 100 | B101: CA-2016-158568 | C101: 42611 | D101: 42409 | E101: Standard Class | F101: RB-19465 | G101: Rick Bensley | H101: Home Office | I101: United States | J101: Chicago | K101: Illinois | L101: 60610 | M101: Central | N101: OFF-PA-10003256 | O101: Office Supplies | P101: Paper | Q101: Avery Personal Creations Heavyweight Cards | R101: 64.624 | S101: 7 | T101: 0.2 | U101: 22.6184
A102: 101 | B102: CA-2016-158568 | C102: 42611 | D102: 42409 | E102: Standard Class | F102: RB-19465 | G102: Rick Bensley | H102: Home Office | I102: United States | J102: Chicago | K102: Illinois | L102: 60610 | M102: Central | N102: TEC-AC-10001767 | O102: Technology | P102: Accessories | Q102: SanDisk Ultra 64 GB MicroSDHC Class 10 Memory Card | R102: 95.976 | S102: 3 | T102: 0.2 | U102: -10.7973
A103: 102 | B103: CA-2016-158568 | C103: 42611 | D103: 42409 | E103: Standard Class | F103: RB-19465 | G103: Rick Bensley | H103: Home Office | I103: United States | J103: Chicago | K103: Illinois | L103: 60610 | M103: Central | N103: OFF-BI-10002609 | O103: Office Supplies | P103: Binders | Q103: Avery Hidden Tab Dividers for Binding Systems | R103: 1.788 | S103: 3 | T103: 0.8 | U103: -3.0396
A104: 103 | B104: CA-2016-129903 | C104: 42705 | D104: 42472 | E104: Second Class | F104: GZ-14470 | G104: Gary Zandusky | H104: Consumer | I104: United States | J104: Rochester | K104: Minnesota | L104: 55901 | M104: Central | N104: OFF-PA-10004040 | O104: Office Supplies | P104: Paper | Q104: Universal Premium White Copier/Laser Paper (20Lb. and 87 Bright) | R104: 23.92 | S104: 4 | T104: 0 | U104: 11.7208
A105: 104 | B105: US-2015-156867 | C105: 42321 | D105: 11/17/2015 | E105: Standard Class | F105: LC-16870 | G105: Lena Cacioppo | H105: Consumer | I105: United States | J105: Aurora | K105: Colorado | L105: 80013 | M105: West | N105: TEC-AC-10001552 | O105: Technology | P105: Accessories | Q105: Logitech K350 2.4Ghz Wireless Keyboard | R105: 238.896 | S105: 6 | T105: 0.2 | U105: -26.8758
A106: 105 | B106: US-2015-156867 | C106: 42321 | D106: 11/17/2015 | E106: Standard Class | F106: LC-16870 | G106: Lena Cacioppo | H106: Consumer | I106: United States | J106: Aurora | K106: Colorado | L106: 80013 | M106: West | N106: FUR-FU-10004006 | O106: Furniture | P106: Furnishings | Q106: Deflect-o DuraMat Lighweight, Studded, Beveled Mat for Low Pile Carpeting | R106: 102.36 | S106: 3 | T106: 0.2 | U106: -3.8385
A107: 106 | B107: US-2015-156867 | C107: 42321 | D107: 11/17/2015 | E107: Standard Class | F107: LC-16870 | G107: Lena Cacioppo | H107: Consumer | I107: United States | J107: Aurora | K107: Colorado | L107: 80013 | M107: West | N107: OFF-BI-10002794 | O107: Office Supplies | P107: Binders | Q107: Avery Trapezoid Ring Binder, 3" Capacity, Black, 1040 sheets | R107: 36.882 | S107: 3 | T107: 0.7 | U107: -25.8174
A108: 107 | B108: CA-2017-119004 | C108: 43062 | D108: 11/28/2017 | E108: Standard Class | F108: JM-15250 | G108: Janet Martin | H108: Consumer | I108: United States | J108: Charlotte | K108: North Carolina | L108: 28205 | M108: South | N108: TEC-AC-10003499 | O108: Technology | P108: Accessories | Q108: Memorex Mini Travel Drive 8 GB USB 2.0 Flash Drive | R108: 74.112 | S108: 8 | T108: 0.2 | U108: 17.6016
A109: 108 | B109: CA-2017-119004 | C109: 43062 | D109: 11/28/2017 | E109: Standard Class | F109: JM-15250 | G109: Janet Martin | H109: Consumer | I109: United States | J109: Charlotte | K109: North Carolina | L109: 28205 | M109: South | N109: TEC-PH-10002844 | O109: Technology | P109: Phones | Q109: Speck Products Candyshell Flip Case | R109: 27.992 | S109: 1 | T109: 0.2 | U109: 2.0994
A110: 109 | B110: CA-2017-119004 | C110: 43062 | D110: 11/28/2017 | E110: Standard Class | F110: JM-15250 | G110: Janet Martin | H110: Consumer | I110: United States | J110: Charlotte | K110: North Carolina | L110: 28205 | M110: South | N110: OFF-AR-10000390 | O110: Office Supplies | P110: Art | Q110: Newell Chalk Holder | R110: 3.304 | S110: 1 | T110: 0.2 | U110: 1.0738
A111: 110 | B111: CA-2015-129476 | C111: 42292 | D111: 10/20/2015 | E111: Standard Class | F111: PA-19060 | G111: Pete Armstrong | H111: Home Office | I111: United States | J111: Orland Park | K111: Illinois | L111: 60462 | M111: Central | N111: TEC-AC-10000844 | O111: Technology | P111: Accessories | Q111: Logitech†Gaming G510s - Keyboard | R111: 339.96 | S111: 5 | T111: 0.2 | U111: 67.992
A112: 111 | B112: CA-2017-146780 | C112: 43094 | D112: 12/30/2017 | E112: Standard Class | F112: CV-12805 | G112: Cynthia Voltz | H112: Corporate | I112: United States | J112: New York City | K112: New York | L112: 10035 | M112: East | N112: FUR-FU-10001934 | O112: Furniture | P112: Furnishings | Q112: Magnifier Swing Arm Lamp | R112: 41.96 | S112: 2 | T112: 0 | U112: 10.9096
A113: 112 | B113: CA-2016-128867 | C113: 42677 | D113: 42654 | E113: Standard Class | F113: CL-12565 | G113: Clay Ludtke | H113: Consumer | I113: United States | J113: Urbandale | K113: Iowa | L113: 50322 | M113: Central | N113: OFF-AR-10000380 | O113: Office Supplies | P113: Art | Q113: Hunt PowerHouse Electric Pencil Sharpener, Blue | R113: 75.96 | S113: 2 | T113: 0 | U113: 22.788
A114: 113 | B114: CA-2016-128867 | C114: 42677 | D114: 42654 | E114: Standard Class | F114: CL-12565 | G114: Clay Ludtke | H114: Consumer | I114: United States | J114: Urbandale | K114: Iowa | L114: 50322 | M114: Central | N114: OFF-BI-10003981 | O114: Office Supplies | P114: Binders | Q114: Avery Durable Plastic 1" Binders | R114: 27.24 | S114: 6 | T114: 0 | U114: 13.3476
A115: 114 | B115: CA-2014-115259 | C115: 41876 | D115: 8/27/2014 | E115: Second Class | F115: RC-19960 | G115: Ryan Crowe | H115: Consumer | I115: United States | J115: Columbus | K115: Ohio | L115: 43229 | M115: East | N115: OFF-FA-10000621 | O115: Office Supplies | P115: Fasteners | Q115: OIC Colored Binder Clips, Assorted Sizes | R115: 40.096 | S115: 14 | T115: 0.2 | U115: 14.5348
A116: 115 | B116: CA-2014-115259 | C116: 41876 | D116: 8/27/2014 | E116: Second Class | F116: RC-19960 | G116: Ryan Crowe | H116: Consumer | I116: United States | J116: Columbus | K116: Ohio | L116: 43229 | M116: East | N116: OFF-EN-10002600 | O116: Office Supplies | P116: Envelopes | Q116: Redi-Strip #10 Envelopes, 4 1/8 x 9 1/2 | R116: 4.72 | S116: 2 | T116: 0.2 | U116: 1.652
A117: 116 | B117: CA-2014-115259 | C117: 41876 | D117: 8/27/2014 | E117: Second Class | F117: RC-19960 | G117: Ryan Crowe | H117: Consumer | I117: United States | J117: Columbus | K117: Ohio | L117: 43229 | M117: East | N117: OFF-PA-10004965 | O117: Office Supplies | P117: Paper | Q117: Xerox 1921 | R117: 23.976 | S117: 3 | T117: 0.2 | U117: 7.4925
...

Sheet Performance Analysis
A1: Month | B1: Current Month Sales | C1: Previous Month Sales | D1: Sales Variance | E1: Growth %
A2: January | B2: {=SUMPRODUCT((MONTH('Sample - Superstore-1'!$C$2:$C$9995)=ROW()-1)*('Sample - Superstore-1'!$R$2:$R$9995))} -> 94924.836
A3: February | B3: {=SUMPRODUCT((MONTH('Sample - Superstore-1'!$C$2:$C$9995)=ROW()-1)*('Sample - Superstore-1'!$R$2:$R$9995))} -> 59751.251 | C3: =B2 -> 94924.836 | D3: =B3-C3 -> -35173.584 | E3: =IF(C3=0,"N/A",ROUND((D3/C3)*100,2)) -> -37.05
A4: March | B4: {=SUMPRODUCT((MONTH('Sample - Superstore-1'!$C$2:$C$9995)=ROW()-1)*('Sample - Superstore-1'!$R$2:$R$9995))} -> 205005.49 | C4: =B3 -> 59751.251 | D4: =B4-C4 -> 145254.24 | E4: =IF(C4=0,"N/A",ROUND((D4/C4)*100,2)) -> 243.1
A5: April | B5: {=SUMPRODUCT((MONTH('Sample - Superstore-1'!$C$2:$C$9995)=ROW()-1)*('Sample - Superstore-1'!$R$2:$R$9995))} -> 137762.13 | C5: =B4 -> 205005.49 | D5: =B5-C5 -> -67243.36 | E5: =IF(C5=0,"N/A",ROUND((D5/C5)*100,2)) -> -32.8
A6: May | B6: {=SUMPRODUCT((MONTH('Sample - Superstore-1'!$C$2:$C$9995)=ROW()-1)*('Sample - Superstore-1'!$R$2:$R$9995))} -> 155028.81 | C6: =B5 -> 137762.13 | D6: =B6-C6 -> 17266.683 | E6: =IF(C6=0,"N/A",ROUND((D6/C6)*100,2)) -> 12.53
A7: June | B7: {=SUMPRODUCT((MONTH('Sample - Superstore-1'!$C$2:$C$9995)=ROW()-1)*('Sample - Superstore-1'!$R$2:$R$9995))} -> 152718.68 | C7: =B6 -> 155028.81 | D7: =B7-C7 -> -2310.1324 | E7: =IF(C7=0,"N/A",ROUND((D7/C7)*100,2)) -> -1.49
A8: July | B8: {=SUMPRODUCT((MONTH('Sample - Superstore-1'!$C$2:$C$9995)=ROW()-1)*('Sample - Superstore-1'!$R$2:$R$9995))} -> 147238.1 | C8: =B7 -> 152718.68 | D8: =B8-C8 -> -5480.5823 | E8: =IF(C8=0,"N/A",ROUND((D8/C8)*100,2)) -> -3.59
A9: August | B9: {=SUMPRODUCT((MONTH('Sample - Superstore-1'!$C$2:$C$9995)=ROW()-1)*('Sample - Superstore-1'!$R$2:$R$9995))} -> 159044.06 | C9: =B8 -> 147238.1 | D9: =B9-C9 -> 11805.966 | E9: =IF(C9=0,"N/A",ROUND((D9/C9)*100,2)) -> 8.02
A10: September | B10: {=SUMPRODUCT((MONTH('Sample - Superstore-1'!$C$2:$C$9995)=ROW()-1)*('Sample - Superstore-1'!$R$2:$R$9995))} -> 307649.95 | C10: =B9 -> 159044.06 | D10: =B10-C10 -> 148605.88 | E10: =IF(C10=0,"N/A",ROUND((D10/C10)*100,2)) -> 93.44
A11: October | B11: {=SUMPRODUCT((MONTH('Sample - Superstore-1'!$C$2:$C$9995)=ROW()-1)*('Sample - Superstore-1'!$R$2:$R$9995))} -> 200322.98 | C11: =B10 -> 307649.95 | D11: =B11-C11 -> -107326.96 | E11: =IF(C11=0,"N/A",ROUND((D11/C11)*100,2)) -> -34.89
A12: November | B12: {=SUMPRODUCT((MONTH('Sample - Superstore-1'!$C$2:$C$9995)=ROW()-1)*('Sample - Superstore-1'!$R$2:$R$9995))} -> 352461.07 | C12: =B11 -> 200322.98 | D12: =B12-C12 -> 152138.09 | E12: =IF(C12=0,"N/A",ROUND((D12/C12)*100,2)) -> 75.95
A13: December | B13: {=SUMPRODUCT((MONTH('Sample - Superstore-1'!$C$2:$C$9995)=ROW()-1)*('Sample - Superstore-1'!$R$2:$R$9995))} -> 325293.5 | C13: =B12 -> 352461.07 | D13: =B13-C13 -> -27167.568 | E13: =IF(C13=0,"N/A",ROUND((D13/C13)*100,2)) -> -7.71
A16: Category | B16: Total Sales | C16: Profit Margin %
A17: Furniture | B17: =SUMIF('Sample - Superstore-1'!$O:$O,"Furniture",'Sample - Superstore-1'!$R:$R) -> 741999.8 | C17: =ROUND(SUMIF('Sample - Superstore-1'!$O:$O,"Furniture",'Sample - Superstore-1'!$U:$U)/B17*100,2) -> 2.49
A18: Office Supplies | B18: =SUMIF('Sample - Superstore-1'!$O:$O,"Office Supplies",'Sample - Superstore-1'!$R:$R) -> 719047.03 | C18: =ROUND(SUMIF('Sample - Superstore-1'!$O:$O,"Office Supplies",'Sample - Superstore-1'!$U:$U)/B18*100,2) -> 17.04
A19: Technology | B19: =SUMIF('Sample - Superstore-1'!$O:$O,"Technology",'Sample - Superstore-1'!$R:$R) -> 836154.03 | C19: =ROUND(SUMIF('Sample - Superstore-1'!$O:$O,"Technology",'Sample - Superstore-1'!$U:$U)/B19*100,2) -> 17.4
